rdflib_endpoint/__init__.py
rdflib_endpoint/__main__.py
rdflib_endpoint/py.typed
rdflib_endpoint/sparql_endpoint.py
rdflib_endpoint/sparql_router.py
rdflib_endpoint/utils.py
rdflib_endpoint/yasgui.html
rdflib_endpoint-0.5.4.dist-info/METADATA
rdflib_endpoint-0.5.4.dist-info/WHEEL
rdflib_endpoint-0.5.4.dist-info/entry_points.txt
rdflib_endpoint-0.5.4.dist-info/licenses/LICENSE.txt
rdflib_endpoint-0.5.4.dist-info/RECORD
