Metadata-Version: 2.4
Name: rdflib-endpoint
Version: 0.5.4
Summary: A package to deploy SPARQL endpoint to serve local RDF files, machine learning models, or any other logic implemented in Python, using RDFLib and FastAPI.
Project-URL: Homepage, https://github.com/vemonet/rdflib-endpoint
Project-URL: Documentation, https://github.com/vemonet/rdflib-endpoint
Project-URL: History, https://github.com/vemonet/rdflib-endpoint/releases
Project-URL: Tracker, https://github.com/vemonet/rdflib-endpoint/issues
Project-URL: Source, https://github.com/vemonet/rdflib-endpoint
Author-email: Vincent Emonet <vincent.emonet@gmail.com>
Maintainer-email: Vincent Emonet <vincent.emonet@gmail.com>
License: MIT License
License-File: LICENSE.txt
Keywords: Python,RDF,RDFLib,SPARQL,endpoint
Classifier: License :: OSI Approved :: MIT License
Classifier: Operating System :: OS Independent
Classifier: Programming Language :: Python :: 3
Classifier: Programming Language :: Python :: 3.8
Classifier: Programming Language :: Python :: 3.9
Classifier: Programming Language :: Python :: 3.10
Classifier: Programming Language :: Python :: 3.11
Classifier: Programming Language :: Python :: 3.12
Classifier: Programming Language :: Python :: 3.13
Requires-Python: >=3.8
Requires-Dist: fastapi>=0.51.0
Requires-Dist: rdflib>=6.0.0
Provides-Extra: cli
Requires-Dist: click; extra == 'cli'
Requires-Dist: uvicorn[standard]>=0.12.0; extra == 'cli'
Provides-Extra: oxigraph
Requires-Dist: oxrdflib; extra == 'oxigraph'
Provides-Extra: web
Requires-Dist: uvicorn[standard]>=0.12.0; extra == 'web'
